Metadata-Version: 2.1
Name: stapy
Version: 0.3.1
Summary: An easy to use SensorThings API Client written in Python
Home-page: https://github.com/zMoooooritz/stapy/
Author: Moritz Biering
Author-email: moritzbiering.mb@gmail.com
License: MIT
Keywords: gis geography ogc data sensor
Classifier: Environment :: Console
Classifier: Development Status :: 4 - Beta
Classifier: Intended Audience :: Developers
Classifier: Intended Audience :: Science/Research
Classifier: License :: OSI Approved :: MIT License
Classifier: Operating System :: OS Independent
Classifier: Programming Language :: Python
Classifier: Programming Language :: Python :: 3
Classifier: Programming Language :: Python :: 3.7
Classifier: Programming Language :: Python :: 3.8
Classifier: Programming Language :: Python :: 3.9
Classifier: Programming Language :: Python :: 3.10
Classifier: Programming Language :: Python :: Implementation :: CPython
Classifier: Programming Language :: Python :: Implementation :: PyPy
Classifier: Topic :: Scientific/Engineering
Classifier: Topic :: Database :: Front-Ends
Classifier: Topic :: Utilities
Requires-Python: >=3.7
License-File: LICENSE
Requires-Dist: geojson (==2.5.0)
Requires-Dist: inquirer (==2.10.0)
Requires-Dist: requests (==2.28.1)
Requires-Dist: setuptools (==65.4.1)
Requires-Dist: thefuzz (==0.19.0)
Requires-Dist: python-dateutil (==2.8.2)
